illumimod/__init__.py
illumimod/_version.py
illumimod/sampling.py
illumimod/masks/__init__.py
illumimod/masks/_apply.py
illumimod/masks/_combine.py
illumimod/masks/_generate.py
illumimod/masks/_scale.py
illumimod-0.2.0.dist-info/licenses/LICENSE
illumimod-0.2.0.dist-info/METADATA
illumimod-0.2.0.dist-info/WHEEL
illumimod-0.2.0.dist-info/top_level.txt
illumimod-0.2.0.dist-info/RECORD
