Metadata-Version: 2.4
Name: illumimod
Version: 0.2.0
Summary: Light simulation for images: RNG pixel pickers, light-to-mask generators, and mask-to-image application.
Author: dooodle74
License: MIT License
Project-URL: Homepage, https://github.com/dooodle74/illumimod
Project-URL: Issues, https://github.com/dooodle74/illumimod/issues
Keywords: image,lighting,augmentation,photography,batch processing,image processing,opencv,numpy
Classifier: Programming Language :: Python :: 3
Classifier: License :: OSI Approved :: MIT License
Classifier: Topic :: Multimedia :: Graphics
Classifier: Intended Audience :: Science/Research
Requires-Python: >=3.9
License-File: LICENSE
Requires-Dist: numpy>=1.23
Provides-Extra: opencv
Requires-Dist: opencv-python>=4.6; extra == "opencv"
Provides-Extra: dev
Requires-Dist: pytest; extra == "dev"
Requires-Dist: ruff; extra == "dev"
Requires-Dist: mypy; extra == "dev"
Requires-Dist: build; extra == "dev"
Requires-Dist: twine; extra == "dev"
Dynamic: license-file
